<?xml version="1.0" ?>
<SmellBaseline>
  <ManuallySuppressedIssues/>
  <CurrentIssues>
    <ID>LongMethod:LibraryScreen.kt:@Composable private fun ScenesGrid</ID>
    <ID>UnusedParameter:FilterSheet.kt:hasSavedDefault: Boolean</ID>
    <ID>UnusedParameter:FilterSheet.kt:onClearDefault: () -&gt; Unit</ID>
    <ID>UnusedParameter:FilterSheet.kt:onSaveAsDefault: (SceneFilter) -&gt; Unit</ID>
    <ID>UnusedParameter:LibraryScreen.kt:onSettingsClick: () -&gt; Unit</ID>
  </CurrentIssues>
</SmellBaseline>
